README.rst
setup.py
imagify/__init__.py
imagify/errors.py
imagify/http_client.py
imagify/imagify.py
imagify_python.egg-info/PKG-INFO
imagify_python.egg-info/SOURCES.txt
imagify_python.egg-info/dependency_links.txt
imagify_python.egg-info/not-zip-safe
imagify_python.egg-info/requires.txt
imagify_python.egg-info/top_level.txt