Metadata-Version: 1.1
Name: imagify-python
Version: 0.0.1
Summary: Imagify API wrapper
Home-page: https://github.com/wp-media/imagify-python
Author: Jean-Baptiste Marchand-Arvier
Author-email: jeanbaptiste@wp-rocket.me
License: MIT License
Download-URL: https://github.com/wp-media/imagify-python/tarball/0.0.1/
Keywords: imagify,python
Platform: UNKNOWN
